[
  {
    "anonymous": false,
    "inputs": [
      {
        "indexed": true,
        "name": "ticket_id",
        "type": "uint256"
      },
      {
        "indexed": true,
        "name": "user_input_address",
        "type": "address"
      },
      {
        "indexed": false,
        "name": "sender",
        "type": "address"
      },
      {
        "indexed": false,
        "name": "anime_fee_paid",
        "type": "uint256"
      }
    ],
    "name": "AnimeMessageSent",
    "type": "event"
  },
  {
    "inputs": [
      {
        "name": "_user_input_address",
        "type": "address"
      }
    ],
    "name": "sendToMainnetContractWithAnime",
    "outputs": [],
    "stateMutability": "payable",
    "type": "function"
  },
  {
    "inputs": [
      {
        "name": "_user_input_address",
        "type": "address"
      },
      {
        "name": "_anime_token_amount",
        "type": "uint256"
      },
      {
        "name": "_max_submission_cost",
        "type": "uint256"
      }
    ],
    "name": "sendWithCustomAnimeAmount",
    "outputs": [],
    "stateMutability": "payable",
    "type": "function"
  },
  {
    "inputs": [],
    "name": "getAnimeTokenAddress",
    "outputs": [
      {
        "name": "",
        "type": "address"
      }
    ],
    "stateMutability": "view",
    "type": "function"
  },
  {
    "inputs": [],
    "name": "getRequiredAnimeApproval",
    "outputs": [
      {
        "name": "",
        "type": "uint256"
      }
    ],
    "stateMutability": "view",
    "type": "function"
  },
  {
    "inputs": [],
    "name": "getMinimumETHForSubmission",
    "outputs": [
      {
        "name": "",
        "type": "uint256"
      }
    ],
    "stateMutability": "view",
    "type": "function"
  },
  {
    "inputs": [
      {
        "name": "_user",
        "type": "address"
      }
    ],
    "name": "checkAnimeAllowance",
    "outputs": [
      {
        "name": "",
        "type": "uint256"
      }
    ],
    "stateMutability": "view",
    "type": "function"
  },
  {
    "inputs": [
      {
        "name": "_user",
        "type": "address"
      }
    ],
    "name": "checkAnimeBalance",
    "outputs": [
      {
        "name": "",
        "type": "uint256"
      }
    ],
    "stateMutability": "view",
    "type": "function"
  },
  {
    "inputs": [
      {
        "name": "_to",
        "type": "address"
      },
      {
        "name": "_amount",
        "type": "uint256"
      }
    ],
    "name": "returnAnimeTokens",
    "outputs": [],
    "stateMutability": "nonpayable",
    "type": "function"
  }
]