{
  "networks": {
    "testnet": {
      "l1": {
        "address": "0xDdc84E4CF833b5AE92A2aA7F4edc59bdcB4b6F0F",
        "contract": "L1QueryOwner"
      },
      "l2": {
        "address": "0x231CFCFD670877CF019BeD1a157aF4C9bfbb7bd9",
        "contract": "L2Relay"
      },
      "l3": {
        "address": "0x233be9576A524299bf9E4633c845ea28FF0868a4",
        "contract": "OwnerRegistry"
      },
      "commissionHub": {
        "address": "",
        "contract": "CommissionHub"
      },
      "artPiece": {
        "address": "",
        "contract": "ArtPiece"
      },
      "profileTemplate": {
        "address": "",
        "contract": "Profile"
      },
      "profileHub": {
        "address": "",
        "contract": "ProfileHub"
      }
    },
    "mainnet": {
      "l1": {
        "address": "0x9Ff3BE6A1f0aa275c61cD231eC3C4469730CC3FD",
        "contract": "L1QueryOwner"
      },
      "l2": {
        "address": "0xf94228517679F83b786C1e4F0ea9042c0c7ceF8c",
        "contract": "L2Relay"
      },
      "l3": {
        "address": "0x51C11796198289c3e3e3AD6e11B137e94ed2e793",
        "contract": "OwnerRegistry"
      },
      "commissionHub": {
        "address": "0x25C570A8D56dc2Ff6e643507DA234F7e668a8541",
        "contract": "CommissionHub"
      },
      "artPiece": {
        "address": "0x83590cBcC7b6C766Aab438b3e371FADee8885646",
        "contract": "ArtPiece"
      },
      "profileTemplate": {
        "address": "0x58785bac268d0cB4cFeC48194A0Fcd6b389B24f9",
        "contract": "Profile"
      },
      "profileHub": {
        "address": "0xF8Ef457CD83981fCEfD3c0Cdba6289101db00EB4",
        "contract": "ProfileHub"
      }
    }
  },
  "lastUpdated": "2025-04-24T20:12:48.981157"
}