{
  "networks": {
    "testnet": {
      "l1": {
        "address": "0x5569B687Bf2070511A65AaEF0A162C4622C5b915",
        "contract": "L1QueryOwnership"
      },
      "l2": {
        "address": "0xD9d3B12A03647fcA5F091e13EB55028c26d1aB42",
        "contract": "L2OwnershipRelay"
      },
      "l3": {
        "address": "0x82B16AA56f8536d1A9d6d5FcC343D44A102d5154",
        "contract": "ArtCommissionHubOwners"
      },
      "artCommissionHub": {
        "address": "0xbFa9FFda0a48fdaf19BCE38Ba89Cf7Bf0c9675Ec",
        "contract": "ArtCommissionHub"
      },
      "artPiece": {
        "address": "0x45B942c424a20fE48b5FfC23548AeA3D085fA5d2",
        "contract": "ArtPiece"
      },
      "profileTemplate": {
        "address": "0xb9cB5930056a3b9547a825EE7D790766f9803184",
        "contract": "Profile"
      },
      "profileFactoryAndRegistry": {
        "address": "0xF16350F5b2a65E3afbe70F3A14d5644a6798CDd6",
        "contract": "ProfileFactoryAndRegistry"
      },
      "profileSocialTemplate": {
        "address": "0x7DF43F3f09f9E485255D1b9b99613d57FAf3fFD9",
        "contract": "ProfileSocial"
      },
      "artEdition1155Template": {
        "address": "0xF0Ed0e9E17adcb413E88dFB5b88cC686558f4B46",
        "contract": "ArtEdition1155"
      },
      "artSales1155Template": {
        "address": "0xa11A699A6Ad838AB08997593eDcb07833393CE5e",
        "contract": "ArtSales1155"
      }
    },
    "mainnet": {
      "l1": {
        "address": "0x8bFE2eA513D1BcB1a7A01aeaD1d4347952CA42e9",
        "contract": "L1QueryOwnership"
      },
      "l2": {
        "address": "0x3cF3dada5C03F32F0b77AAE7Ae19F61Ab89dbD06",
        "contract": "L2OwnershipRelay"
      },
      "l3": {
        "address": "0xAb2fa091126f49E6b3B808426776aC139F0BD0b3",
        "contract": "ArtCommissionHubOwners"
      },
      "artCommissionHub": {
        "address": "0x09517E1e6eA9803f8AB5Ba608d5985D098CdBdd8",
        "contract": "ArtCommissionHub"
      },
      "artPiece": {
        "address": "0x48015942F03b850bf4e0b1ea285b9E5cdB3fBcC6",
        "contract": "ArtPiece"
      },
      "profileTemplate": {
        "address": "0x61D2C3d1D344e72184Cb813840502fF7c51719E3",
        "contract": "Profile"
      },
      "profileFactoryAndRegistry": {
        "address": "0x09F9D4aAcDed38355e55226e80472e70016Ae3b7",
        "contract": "ProfileFactoryAndRegistry"
      },
      "profileSocialTemplate": {
        "address": "0xC2fe14e67063fCF4A88ca1E50BF1CE49D9cF1c39",
        "contract": "ProfileSocial"
      }
    }
  },
  "lastUpdated": "2025-06-10T22:13:04.918596"
}